{
  "Actions": [
    {
      "Icon": "images/actions/mute",
      "Name": "Mute Toggle",
      "States": [
        {
          "Image": "images/states/muted",
          "TitleAlignment": "middle",
          "FontSize": "16"
        }
      ],
      "SupportedInMultiActions": true,
      "Tooltip": "Toggle microphone mute in Google Meet",
      "UUID": "com.kolaborate.googlemeet.mute"
    },
    {
      "Icon": "images/actions/video",
      "Name": "Video Toggle",
      "States": [
        {
          "Image": "images/states/video-off",
          "TitleAlignment": "middle",
          "FontSize": "16"
        }
      ],
      "SupportedInMultiActions": true,
      "Tooltip": "Toggle video in Google Meet",
      "UUID": "com.kolaborate.googlemeet.video"
    },
    {
      "Icon": "images/actions/hand",
      "Name": "Hand Raise",
      "States": [
        {
          "Image": "images/states/hand-down",
          "TitleAlignment": "middle",
          "FontSize": "16"
        }
      ],
      "SupportedInMultiActions": true,
      "Tooltip": "Toggle hand raise in Google Meet",
      "UUID": "com.kolaborate.googlemeet.hand"
    },
    {
      "Icon": "images/actions/chat",
      "Name": "Chat Toggle",
      "States": [
        {
          "Image": "images/states/chat-closed",
          "TitleAlignment": "middle",
          "FontSize": "16"
        }
      ],
      "SupportedInMultiActions": true,
      "Tooltip": "Toggle chat panel in Google Meet",
      "UUID": "com.kolaborate.googlemeet.chat"
    }
  ],
  "Author": "Kolaborate",
  "Description": "Control Google Meet directly from your Stream Deck",
  "Name": "Google Meet Controls",
  "Icon": "images/pluginIcon",
  "URL": "https://kolaborate.africa",
  "Version": "1.0.0",
  "CodePath": "plugin/com.kolaborate.googlemeet",
  "PropertyInspectorPath": "propertyinspector/index.html",
  "Category": "Google Meet",
  "CategoryIcon": "images/categoryIcon",
  "OS": [
    {
      "Platform": "mac",
      "MinimumVersion": "10.11"
    },
    {
      "Platform": "windows",
      "MinimumVersion": "10"
    }
  ],
  "SDKVersion": 2,
  "Software": {
    "MinimumVersion": "4.1"
  },
  "Files": {
    "mac": {
      "third-party": {
        "node": "8.x"
      }
    },
    "windows": {
      "third-party": {
        "node": "8.x"
      }
    }
  },
  "ApplicationsToMonitor": {
    "windows": [
      "chrome.exe",
      "msedge.exe",
      "firefox.exe"
    ],
    "mac": [
      "Google Chrome",
      "Microsoft Edge",
      "Firefox"
    ]
  }
}